{
  "definitionName": "vProductAndDescription",
  "schemaName": "Production",
  "definition": "CREATE VIEW [Production].[vProductAndDescription]\nWITH SCHEMABINDING AS\nSELECT\n    p.[ProductID],\n    p.[Name],\n    pm.[Name] AS [ProductModel],\n    pmx.[CultureID],\n    pd.[Description]\nFROM  \n    [Production].[Product] AS p INNER JOIN\n    [Production].[ProductModel] AS pm ON\n         p.[ProductModelID] = pm.[ProductModelID] INNER JOIN\n    [Production].[ProductModelProductDescriptionCulture] AS pmx ON\n         pm.[ProductModelID] = pmx.[ProductModelID] INNER JOIN\n    [Production].[ProductDescription] AS pd ON\n         pmx.[ProductDescriptionID] = pd.[ProductDescriptionID];",
  "xType": "V",
  "type": "VIEW",
  "view": {
    "tableName": "vProductAndDescription",
    "schemaName": "Production",
    "temporalType": 0,
    "isMemoryOptimized": false,
    "isExternal": false,
    "isView": true,
    "columns": [
      {
        "schemaName": "Production",
        "columnName": "ProductID",
        "columnId": 1,
        "isPrimaryKey": false,
        "precision": 10,
        "scale": 0,
        "isNullable": false,
        "isIdentity": false,
        "isComputed": false,
        "isHidden": false,
        "generatedAlwaysType": 0,
        "columnType": "INT",
        "extendedProperties": {}
      },
      {
        "schemaName": "Production",
        "columnName": "Name",
        "columnId": 2,
        "isPrimaryKey": false,
        "precision": 100,
        "scale": 0,
        "isNullable": false,
        "isIdentity": false,
        "isComputed": false,
        "isHidden": false,
        "generatedAlwaysType": 0,
        "columnType": "NAME",
        "extendedProperties": {}
      },
      {
        "schemaName": "Production",
        "columnName": "ProductModel",
        "columnId": 3,
        "isPrimaryKey": false,
        "precision": 100,
        "scale": 0,
        "isNullable": false,
        "isIdentity": false,
        "isComputed": false,
        "isHidden": false,
        "generatedAlwaysType": 0,
        "columnType": "NAME",
        "extendedProperties": {}
      },
      {
        "schemaName": "Production",
        "columnName": "CultureID",
        "columnId": 4,
        "isPrimaryKey": false,
        "precision": 6,
        "scale": 0,
        "isNullable": false,
        "isIdentity": false,
        "isComputed": false,
        "isHidden": false,
        "generatedAlwaysType": 0,
        "columnType": "NCHAR",
        "extendedProperties": {}
      },
      {
        "schemaName": "Production",
        "columnName": "Description",
        "columnId": 5,
        "isPrimaryKey": false,
        "precision": 400,
        "scale": 0,
        "isNullable": false,
        "isIdentity": false,
        "isComputed": false,
        "isHidden": false,
        "generatedAlwaysType": 0,
        "columnType": "NVARCHAR",
        "extendedProperties": {}
      }
    ],
    "extendedProperties": {}
  }
}